COPYRIGHT
MANIFEST.in
README
setup.cfg
setup.py
appengine_stubs/cookielib.py
appengine_stubs/urllib_stub.py
appengine_stubs/urlparse.py
examples/get_albums.py
examples/freebase-images-appengine/README
examples/freebase-images-appengine/app.yaml
examples/freebase-images-appengine/hello.py
examples/freebase-images-appengine/index.html
examples/freebase-images-appengine/index.yaml
examples/freebase-images-appengine/freebase/__init__.py
examples/freebase-images-appengine/freebase/__init__.pyc
examples/freebase-images-appengine/freebase/rison.py
examples/freebase-images-appengine/freebase/sandbox.py
examples/freebase-images-appengine/freebase/sandbox.pyc
examples/freebase-images-appengine/freebase/uritemplate.py
examples/freebase-images-appengine/freebase/api/__init__.py
examples/freebase-images-appengine/freebase/api/__init__.pyc
examples/freebase-images-appengine/freebase/api/cookie_handlers.py
examples/freebase-images-appengine/freebase/api/cookie_handlers.pyc
examples/freebase-images-appengine/freebase/api/httpclients.py
examples/freebase-images-appengine/freebase/api/httpclients.pyc
examples/freebase-images-appengine/freebase/api/mqlkey.py
examples/freebase-images-appengine/freebase/api/mqlkey.pyc
examples/freebase-images-appengine/freebase/api/session.py
examples/freebase-images-appengine/freebase/api/session.pyc
examples/freebase-images-appengine/freebase/fcl/README.txt
examples/freebase-images-appengine/freebase/fcl/__init__.py
examples/freebase-images-appengine/freebase/fcl/commands.py
examples/freebase-images-appengine/freebase/fcl/fbutil.py
examples/freebase-images-appengine/freebase/fcl/fcl.py
examples/freebase-images-appengine/freebase/fcl/inspect.py
examples/freebase-images-appengine/freebase/fcl/mktype.py
examples/freebase-images-appengine/javascript/freebase.select.js
examples/freebase-images-appengine/javascript/freebase.suggest.js
examples/freebase-images-appengine/stylesheets/button_bkd.gif
examples/freebase-images-appengine/stylesheets/down-arrow.gif
freebase.egg-info/PKG-INFO
freebase.egg-info/SOURCES.txt
freebase.egg-info/dependency_links.txt
freebase.egg-info/entry_points.txt
freebase.egg-info/requires.txt
freebase.egg-info/top_level.txt
